echofish_aws_create_empty_zarr_store_lambda/__init__.py
echofish_aws_create_empty_zarr_store_lambda/dynamo_operations.py
echofish_aws_create_empty_zarr_store_lambda/lambda_executor.py
echofish_aws_create_empty_zarr_store_lambda/lambda_handler.py
echofish_aws_create_empty_zarr_store_lambda/s3_operations.py
echofish_aws_create_empty_zarr_store_lambda/sns_operations.py
echofish_aws_create_empty_zarr_store_lambda-1.0.1.dist-info/LICENSE
echofish_aws_create_empty_zarr_store_lambda-1.0.1.dist-info/METADATA
echofish_aws_create_empty_zarr_store_lambda-1.0.1.dist-info/WHEEL
echofish_aws_create_empty_zarr_store_lambda-1.0.1.dist-info/top_level.txt
echofish_aws_create_empty_zarr_store_lambda-1.0.1.dist-info/RECORD
