Metadata-Version: 2.1
Name: echofish-aws-create-empty-zarr-store-lambda
Version: 1.0.1
Home-page: https://github.com/ci-cmg/echofish-aws-create-empty-zarr-store-lambda
Classifier: Programming Language :: Python :: 3.9
Classifier: License :: OSI Approved :: MIT License
Requires-Python: >=3.9
License-File: LICENSE
Requires-Dist: pandas ==1.5.3
Requires-Dist: numpy ==1.23.4
Requires-Dist: zarr ==2.16.1
Requires-Dist: xarray ==2022.3.0
Requires-Dist: boto3 ==1.26.165
Requires-Dist: botocore ==1.29.165
Requires-Dist: typing-extensions ==4.8.0
Requires-Dist: numcodecs ==0.11.0
